tussik/__init__.py
tussik/zpl/__init__.py
tussik/zpl/zplconfig.py
tussik/zpl/zplwriter.py
tussik.zpl-0.1.0rc1.dist-info/LICENSE
tussik.zpl-0.1.0rc1.dist-info/METADATA
tussik.zpl-0.1.0rc1.dist-info/WHEEL
tussik.zpl-0.1.0rc1.dist-info/top_level.txt
tussik.zpl-0.1.0rc1.dist-info/zip-safe
tussik.zpl-0.1.0rc1.dist-info/RECORD
